py3ioc/__init__.py
py3ioc/containers.py
py3ioc/locators.py
py3ioc/providers.py
py3ioc-1.0.1.dist-info/METADATA
py3ioc-1.0.1.dist-info/WHEEL
py3ioc-1.0.1.dist-info/top_level.txt
py3ioc-1.0.1.dist-info/RECORD
